{
  "id": "a8b5c6d7-e8f9-4a5b-6c7d-8e9f0a1b2c3d",
  "name": "Pavillon Les Lys - Development",
  "values": [
    {
      "key": "base_url",
      "value": "http://localhost:3000",
      "type": "default",
      "enabled": true
    },
    {
      "key": "access_token",
      "value": "",
      "type": "secret",
      "enabled": true
    },
    {
      "key": "user_id",
      "value": "",
      "type": "default",
      "enabled": true
    },
    {
      "key": "reservation_id",
      "value": "",
      "type": "default",
      "enabled": true
    },
    {
      "key": "payment_id",
      "value": "",
      "type": "default",
      "enabled": true
    },
    {
      "key": "quote_id",
      "value": "",
      "type": "default",
      "enabled": true
    },
    {
      "key": "feedback_id",
      "value": "",
      "type": "default",
      "enabled": true
    },
    {
      "key": "item_id",
      "value": "",
      "type": "default",
      "enabled": true
    }
  ],
  "_postman_variable_scope": "environment",
  "_postman_exported_at": "2024-01-15T12:00:00.000Z",
  "_postman_exported_using": "Postman/10.20.0"
}
